MANIFEST.in
README.rst
Readme.rst
distribute_setup.py
setup.py
shtest.py
shtest.egg-info/PKG-INFO
shtest.egg-info/SOURCES.txt
shtest.egg-info/dependency_links.txt
shtest.egg-info/entry_points.txt
shtest.egg-info/requires.txt
shtest.egg-info/top_level.txt