Metadata-Version: 1.0
Name: shtest
Version: 0.2
Summary: Test runner run executable as tests
Home-page: https://github.com/thasso/shtest
Author: Thasso Griebel
Author-email: thasso.griebel@gmail.com
License: BSD
Platform: UNKNOWN
